soauth/__init__.py
soauth/main.py
soauth/soauth.py
SoAuth-1.0.5.dist-info/METADATA
SoAuth-1.0.5.dist-info/WHEEL
SoAuth-1.0.5.dist-info/top_level.txt
SoAuth-1.0.5.dist-info/RECORD
