Metadata-Version: 2.1
Name: SoAuth
Version: 1.0.5
Summary: Flask middleware for SoAuth
Home-page: https://github.com/sojs-coder/SoAuth-Py
Author: SoJS
Author-email: sojs_coder@protonmail.com
License: ISC
Requires-Dist: requests
Requires-Dist: flask
